rapid_doc/__init__.py
rapid_doc/version.py
rapid_doc/backend/__init__.py
rapid_doc/backend/utils.py
rapid_doc/backend/pipeline/__init__.py
rapid_doc/backend/pipeline/batch_analyze.py
rapid_doc/backend/pipeline/model_init.py
rapid_doc/backend/pipeline/model_json_to_middle_json.py
rapid_doc/backend/pipeline/model_list.py
rapid_doc/backend/pipeline/para_split.py
rapid_doc/backend/pipeline/pipeline_analyze.py
rapid_doc/backend/pipeline/pipeline_magic_model.py
rapid_doc/backend/pipeline/pipeline_middle_json_mkcontent.py
rapid_doc/cli/__init__.py
rapid_doc/cli/common.py
rapid_doc/cli/gradio_app.py
rapid_doc/data/__init__.py
rapid_doc/data/data_reader_writer/__init__.py
rapid_doc/data/data_reader_writer/base.py
rapid_doc/data/data_reader_writer/dummy.py
rapid_doc/data/data_reader_writer/filebase.py
rapid_doc/data/data_reader_writer/multi_bucket_s3.py
rapid_doc/data/data_reader_writer/s3.py
rapid_doc/data/io/__init__.py
rapid_doc/data/io/base.py
rapid_doc/data/io/http.py
rapid_doc/data/io/s3.py
rapid_doc/data/utils/__init__.py
rapid_doc/data/utils/exceptions.py
rapid_doc/data/utils/path_utils.py
rapid_doc/data/utils/schemas.py
rapid_doc/model/__init__.py
rapid_doc/model/formula/__init__.py
rapid_doc/model/formula/fix_utils.py
rapid_doc/model/formula/rapid_formula_model.py
rapid_doc/model/formula/rapid_formula_self/__init__.py
rapid_doc/model/formula/rapid_formula_self/main.py
rapid_doc/model/formula/rapid_formula_self/configs/__init__.py
rapid_doc/model/formula/rapid_formula_self/configs/default_models.yaml
rapid_doc/model/formula/rapid_formula_self/configs/engine_cfg.yaml
rapid_doc/model/formula/rapid_formula_self/inference_engine/__init__.py
rapid_doc/model/formula/rapid_formula_self/inference_engine/base.py
rapid_doc/model/formula/rapid_formula_self/inference_engine/openvino.py
rapid_doc/model/formula/rapid_formula_self/inference_engine/torch.py
rapid_doc/model/formula/rapid_formula_self/inference_engine/onnxruntime/__init__.py
rapid_doc-0.6.1.dist-info/licenses/LICENSE
rapid_doc-0.6.1.dist-info/METADATA
rapid_doc-0.6.1.dist-info/WHEEL
rapid_doc-0.6.1.dist-info/top_level.txt
rapid_doc-0.6.1.dist-info/RECORD
