Metadata-Version: 2.4
Name: rapid-doc
Version: 0.6.1
Summary: A practical tool for converting PDF to Markdown
License: Apache-2.0
Project-URL: homepage, https://github.com/RapidAI
Project-URL: repository, https://github.com/RapidAI/RapidOCR
Project-URL: issues, https://github.com/RapidAI/RapidOCR/issues
Keywords: rapid-doc, rapid_doc, onnx, convert, pdf, markdown
Classifier: Programming Language :: Python :: 3.10
Classifier: Programming Language :: Python :: 3.11
Classifier: Programming Language :: Python :: 3.12
Classifier: Programming Language :: Python :: 3.13
Requires-Python: <3.14,>=3.10
License-File: LICENSE
Requires-Dist: boto3>=1.28.43
Requires-Dist: loguru>=0.6.0
Requires-Dist: numpy>=1.21.6
Requires-Dist: pdfminer.six==20250506
Requires-Dist: tqdm>=4.67.1
Requires-Dist: requests
Requires-Dist: pypdfium2>=4.30.0
Requires-Dist: pypdf>=5.6.0
Requires-Dist: reportlab
Requires-Dist: pdftext>=0.6.2
Requires-Dist: json-repair>=0.46.2
Requires-Dist: fast-langdetect<0.3.0,>=0.2.3
Requires-Dist: scikit-image<1.0.0,>=0.25.0
Requires-Dist: beautifulsoup4<5,>=4.13.5
Requires-Dist: pydantic<2.11,>=2.7.2
Requires-Dist: matplotlib<4,>=3.10
Requires-Dist: ftfy<7,>=6.3.1
Requires-Dist: shapely<3,>=2.0.7
Requires-Dist: tokenizers>=0.13.2
Requires-Dist: rapidocr<=3.4.3,>=3.4.0
Provides-Extra: test
Requires-Dist: rapid-doc[cpu]; extra == "test"
Requires-Dist: pytest; extra == "test"
Requires-Dist: fuzzywuzzy; extra == "test"
Provides-Extra: cpu
Requires-Dist: onnxruntime>=1.18.0; extra == "cpu"
Requires-Dist: openvino<=2025.4.0,>=2024.6.0; extra == "cpu"
Provides-Extra: gpu
Requires-Dist: onnxruntime-gpu<=1.23.0; extra == "gpu"
Requires-Dist: torch<3,>=2.6.0; extra == "gpu"
Requires-Dist: torchvision; extra == "gpu"
Provides-Extra: api
Requires-Dist: fastapi>=0.104.0; extra == "api"
Requires-Dist: uvicorn[standard]>=0.24.0; extra == "api"
Requires-Dist: python-multipart>=0.0.6; extra == "api"
Provides-Extra: word
Requires-Dist: python-docx>=0.8.10; extra == "word"
Requires-Dist: pypandoc-binary; extra == "word"
Provides-Extra: html
Requires-Dist: markdown-it-py; extra == "html"
Requires-Dist: mdit-py-plugins; extra == "html"
Requires-Dist: pygments; extra == "html"
Provides-Extra: gradio
Requires-Dist: gradio<6,>=5.34; extra == "gradio"
Requires-Dist: gradio-pdf>=0.0.22; extra == "gradio"
Provides-Extra: core
Requires-Dist: openvino>=2024.6.0; extra == "core"
Requires-Dist: onnxruntime-gpu<=1.23.0; extra == "core"
Requires-Dist: torch<3,>=2.6.0; extra == "core"
Requires-Dist: torchvision; extra == "core"
Provides-Extra: npu
Requires-Dist: numpy<2,>=1.21.6; extra == "npu"
Requires-Dist: decorator; extra == "npu"
Requires-Dist: attrs; extra == "npu"
Requires-Dist: psutil; extra == "npu"
Requires-Dist: onnxruntime-cann==1.22.0; extra == "npu"
Requires-Dist: torch==2.5.1; extra == "npu"
Requires-Dist: torch-npu==2.5.1; extra == "npu"
Requires-Dist: torchvision; extra == "npu"
Dynamic: license-file
